pyaltium/__init__.py
pyaltium/base.py
pyaltium/exceptions.py
pyaltium/matlib/__init__.py
pyaltium/matlib/_helpers.py
pyaltium/matlib/_lib.py
pyaltium/matlib/base.py
pyaltium/matlib/types.py
pyaltium/pcb/__init__.py
pyaltium/pcb/_lib.py
pyaltium/pcb/_record.py
pyaltium/sch/__init__.py
pyaltium/sch/_helpers.py
pyaltium/sch/_item.py
pyaltium/sch/_lib.py
pyaltium/sch/_record.py
PyAltium-0.4.0.dist-info/LICENSE
PyAltium-0.4.0.dist-info/METADATA
PyAltium-0.4.0.dist-info/WHEEL
PyAltium-0.4.0.dist-info/top_level.txt
PyAltium-0.4.0.dist-info/RECORD
