Metadata-Version: 2.1
Name: PyAltium
Version: 0.4.0
Summary: A package for reading Altium files
Home-page: https://github.com/pluots/PyAltium
Author: Trevor Gross
Author-email: t.gross35@gmail.com
Project-URL: Bug Tracker, https://github.com/pluots/PyAltium/issues
Classifier: Programming Language :: Python :: 3
Classifier: License :: OSI Approved :: MIT License
Classifier: Operating System :: OS Independent
Requires-Python: >=3.7
License-File: LICENSE
